{
  "timestamp": "2026-01-21T00:00:48Z",
  "rawFrontendInitData": {
    "backendState": {
      "eTag": "f805021e4c8211b5",
      "loadControlEnabled": "0",
      "emergencyBannerSettings": {
        "bannerEnabled": 1,
        "bannerMessage": "Treat all lines as live",
        "bannerType": "info",
        "bannerExcerpt": "Treat all lines as live",
        "bannerMessageWebURLSupport": []
      },
      "mapOverrides": {
        "showNorth": 0,
        "showSouth": 0
      }
    },
    "lastEtag": "f805021e4c8211b5",
    "lastMapOverrides": {
      "showNorth": 0,
      "showSouth": 0
    },
    "markers": {
      "unplanned": [
        {
          "id": "36593F",
          "lat": -35.24301848078365,
          "lng": 173.3058788197403
        }
      ],
      "planned": [
        {
          "id": "35945F",
          "lat": -35.27745653178012,
          "lng": 174.18001728131168
        },
        {
          "id": "35969F",
          "lat": -35.193942794678826,
          "lng": 174.02850122626688
        },
        {
          "id": "36038F",
          "lat": -34.980953748107545,
          "lng": 173.66985502128912
        },
        {
          "id": "36212F",
          "lat": -35.44737640804392,
          "lng": 174.14595454394595
        },
        {
          "id": "36260F",
          "lat": -35.38438927605359,
          "lng": 173.60211042110404
        },
        {
          "id": "36266F",
          "lat": -35.043952843455344,
          "lng": 173.70872946968709
        },
        {
          "id": "36329F",
          "lat": -35.11658679236681,
          "lng": 173.46353532879448
        },
        {
          "id": "36341F",
          "lat": -35.37844906897818,
          "lng": 174.0756835613388
        },
        {
          "id": "36344F",
          "lat": -35.11973893605652,
          "lng": 173.32856895284033
        },
        {
          "id": "36374F",
          "lat": -35.12856903469989,
          "lng": 173.44962310875715
        },
        {
          "id": "36389F",
          "lat": -35.2555966368212,
          "lng": 174.20617718475967
        },
        {
          "id": "36449F",
          "lat": -35.00236454267577,
          "lng": 173.59489453935626
        },
        {
          "id": "36575F",
          "lat": -35.20791080304029,
          "lng": 173.9367340519322
        },
        {
          "id": "36590F",
          "lat": -35.24709448664867,
          "lng": 173.89950941589743
        }
      ],
      "plannedActive": []
    },
    "outageList": {
      "customersCurrentlyOff": 7,
      "activeOutageCount": 1,
      "planned": [
        {
          "type": "planned",
          "name": "36575F",
          "startTimestamp": 1769023800,
          "isActive": false,
          "circuitName": "Riverview",
          "customersCurrentlyOff": "35",
          "startDateTime": "22nd January 08:30 am",
          "endDateTime": "22nd January 08:45 am",
          "alternativeStartDateTime": "27th January 08:30 am",
          "alternativeEndDateTime": "27th January 08:45 am",
          "additionalInformation": ""
        },
        {
          "type": "planned",
          "name": "36038F",
          "startTimestamp": 1769027400,
          "isActive": false,
          "circuitName": "Oruru",
          "customersCurrentlyOff": "233",
          "startDateTime": "22nd January 09:30 am",
          "endDateTime": "22nd January 03:30 pm",
          "alternativeStartDateTime": "23rd January 09:30 am",
          "alternativeEndDateTime": "23rd January 03:30 pm",
          "additionalInformation": ""
        },
        {
          "type": "planned",
          "name": "36212F",
          "startTimestamp": 1769029200,
          "isActive": false,
          "circuitName": "Towai",
          "customersCurrentlyOff": "22",
          "startDateTime": "22nd January 10:00 am",
          "endDateTime": "22nd January 02:00 pm",
          "alternativeStartDateTime": "28th January 10:00 am",
          "alternativeEndDateTime": "28th January 02:00 pm",
          "additionalInformation": ""
        },
        {
          "type": "planned",
          "name": "36449F",
          "startTimestamp": 1769113800,
          "isActive": false,
          "circuitName": "Oruru",
          "customersCurrentlyOff": "6",
          "startDateTime": "23rd January 09:30 am",
          "endDateTime": "23rd January 12:30 pm",
          "alternativeStartDateTime": "27th January 09:30 am",
          "alternativeEndDateTime": "27th January 12:30 pm",
          "additionalInformation": ""
        },
        {
          "type": "planned",
          "name": "35945F",
          "startTimestamp": 1769457600,
          "isActive": false,
          "circuitName": "Russell Express",
          "customersCurrentlyOff": "6",
          "startDateTime": "27th January 09:00 am",
          "endDateTime": "27th January 02:30 pm",
          "alternativeStartDateTime": "28th January 09:00 am",
          "alternativeEndDateTime": "28th January 02:30 pm",
          "additionalInformation": ""
        },
        {
          "type": "planned",
          "name": "35969F",
          "startTimestamp": 1769459400,
          "isActive": false,
          "circuitName": "Purerua",
          "customersCurrentlyOff": "47",
          "startDateTime": "27th January 09:30 am",
          "endDateTime": "27th January 03:00 pm",
          "alternativeStartDateTime": "2nd February 09:30 am",
          "alternativeEndDateTime": "2nd February 03:00 pm",
          "additionalInformation": ""
        },
        {
          "type": "planned",
          "name": "36329F",
          "startTimestamp": 1769459400,
          "isActive": false,
          "circuitName": "Oruru",
          "customersCurrentlyOff": "112",
          "startDateTime": "27th January 09:30 am",
          "endDateTime": "27th January 03:30 pm",
          "alternativeStartDateTime": "30th January 09:30 am",
          "alternativeEndDateTime": "30th January 03:30 pm",
          "additionalInformation": ""
        },
        {
          "type": "planned",
          "name": "36341F",
          "startTimestamp": 1769545800,
          "isActive": false,
          "circuitName": "Opua",
          "customersCurrentlyOff": "228",
          "startDateTime": "28th January 09:30 am",
          "endDateTime": "28th January 02:30 pm",
          "alternativeStartDateTime": "2nd February 09:30 am",
          "alternativeEndDateTime": "2nd February 02:30 pm",
          "additionalInformation": ""
        },
        {
          "type": "planned",
          "name": "36260F",
          "startTimestamp": 1769549400,
          "isActive": false,
          "circuitName": "Horeke",
          "customersCurrentlyOff": "9",
          "startDateTime": "28th January 10:30 am",
          "endDateTime": "28th January 03:00 pm",
          "alternativeStartDateTime": "28th January 10:30 am",
          "alternativeEndDateTime": "28th January 03:00 pm",
          "additionalInformation": ""
        },
        {
          "type": "planned",
          "name": "36389F",
          "startTimestamp": 1769630400,
          "isActive": false,
          "circuitName": "Russell Express",
          "customersCurrentlyOff": "25",
          "startDateTime": "29th January 09:00 am",
          "endDateTime": "29th January 03:00 pm",
          "alternativeStartDateTime": "29th January 09:00 am",
          "alternativeEndDateTime": "29th January 03:00 pm",
          "additionalInformation": ""
        },
        {
          "type": "planned",
          "name": "36266F",
          "startTimestamp": 1769634000,
          "isActive": false,
          "circuitName": "Totara North",
          "customersCurrentlyOff": "7",
          "startDateTime": "29th January 10:00 am",
          "endDateTime": "29th January 01:00 pm",
          "alternativeStartDateTime": "2nd February 10:00 am",
          "alternativeEndDateTime": "2nd February 01:00 pm",
          "additionalInformation": ""
        },
        {
          "type": "planned",
          "name": "36344F",
          "startTimestamp": 1769634000,
          "isActive": false,
          "circuitName": "Sub-transmission",
          "customersCurrentlyOff": "19",
          "startDateTime": "29th January 10:00 am",
          "endDateTime": "29th January 03:00 pm",
          "alternativeStartDateTime": "30th January 10:00 am",
          "alternativeEndDateTime": "30th January 03:00 pm",
          "additionalInformation": ""
        },
        {
          "type": "planned",
          "name": "36374F",
          "startTimestamp": 1769716800,
          "isActive": false,
          "circuitName": "Oxford Street",
          "customersCurrentlyOff": "24",
          "startDateTime": "30th January 09:00 am",
          "endDateTime": "30th January 03:30 pm",
          "alternativeStartDateTime": "2nd February 09:00 am",
          "alternativeEndDateTime": "2nd February 03:30 pm",
          "additionalInformation": ""
        },
        {
          "type": "planned",
          "name": "36590F",
          "startTimestamp": 1769720400,
          "isActive": false,
          "circuitName": "Crossroads",
          "customersCurrentlyOff": "75",
          "startDateTime": "30th January 10:00 am",
          "endDateTime": "30th January 12:30 pm",
          "alternativeStartDateTime": "2nd February 10:00 am",
          "alternativeEndDateTime": "2nd February 12:30 pm",
          "additionalInformation": ""
        }
      ],
      "active": [
        {
          "type": "unplanned",
          "name": "36593F",
          "startTimestamp": 1768939560,
          "isActive": true,
          "circuitName": "South Road",
          "customersCurrentlyOff": "7",
          "startDateTime": "21st January 09:06 am",
          "endDateTime": "21st January 03:06 pm",
          "alternativeStartDateTime": "",
          "alternativeEndDateTime": "",
          "additionalInformation": ""
        }
      ]
    }
  },
  "detailedOutageInfo": {
    "36593F": {
      "duration": "Unknown",
      "startDate": "21/01/2026",
      "startTime": "09:06 AM",
      "estimatedRestorationDate": "21/01/2026",
      "estimatedRestorationTime": "03:06 PM",
      "alternativeStartDate": "",
      "alternativeStartTime": "",
      "alternativeEstimatedRestorationDate": "",
      "alternativeEstimatedRestorationTime": "",
      "additionalInformation": "",
      "cause": "Under Investigation",
      "suburbs": "BROADWOOD, HEREKINO",
      "noticeType": "Unplanned",
      "streets": {
        "showStreets": "EATON ROAD, WAIOTEHUE ROAD",
        "hiddenStreets": ""
      },
      "customersAffected": "7",
      "feeder": "SOUTH ROAD",
      "lastUpdateTime": "21/01/2026 10:07 AM",
      "status": "Active",
      "offsupply": "1"
    }
  }
}